wifireconnect
