Metadata-Version: 2.1
Name: wifireconnect
Version: 0.1.1
Summary: Python3 module to test and ensure connectivity on a network which have stability problems on traffic routing (link layer).
Home-page: https://github.com/carlosplanchon/wifireconnect
Author: Carlos A. Planchón
Author-email: bubbledoloresuruguay2@gmail.com
License: GPL3
Download-URL: https://github.com/carlosplanchon/wifireconnect/archive/v0.1.1.tar.gz
Keywords: wifi,connectivity,networking
Platform: UNKNOWN
Classifier: Intended Audience :: Developers
Classifier: Topic :: Software Development :: Build Tools
Classifier: License :: OSI Approved :: GNU General Public License v3 (GPLv3)
Classifier: Programming Language :: Python :: 3.7
